ansitable/__init__.py
ansitable/table.py
ansitable-0.11.3.dist-info/LICENSE
ansitable-0.11.3.dist-info/METADATA
ansitable-0.11.3.dist-info/WHEEL
ansitable-0.11.3.dist-info/top_level.txt
ansitable-0.11.3.dist-info/RECORD
