Metadata-Version: 2.1
Name: ansitable
Version: 0.11.3
Summary: Quick and easy display of tabular data and matrices with optional ANSI color and borders
Author-email: Peter Corke <rvc@petercorke.com>
Project-URL: Homepage, https://github.com/petercorke/ansitable
Project-URL: Bug Tracker, https://github.com/petercorke/ansitable/issues
Project-URL: Documentation, https://github.io/petercorke/ansitable
Project-URL: Source, https://github.com/petercorke/ansitable
Keywords: table,table layout,table format,tabular,tabular layout,tabular format,Pandas,ANSI,ANSI art,ANSI box characters,color,ANSI color,matrix display,CSV,Markdown table,HTML table,LaTeX table,ReStructuredText table,wikitable table
Classifier: Development Status :: 5 - Production/Stable
Classifier: Intended Audience :: Developers
Classifier: Programming Language :: Python :: 3.4
Classifier: Programming Language :: Python :: 3.5
Classifier: Programming Language :: Python :: 3.6
Classifier: Programming Language :: Python :: 3.7
Classifier: Programming Language :: Python :: 3.8
Classifier: Programming Language :: Python :: 3.9
Classifier: Programming Language :: Python :: 3.10
Classifier: Programming Language :: Python :: 3.11
Classifier: Programming Language :: Python :: 3.12
Classifier: License :: OSI Approved :: MIT License
Classifier: Operating System :: OS Independent
Requires-Python: >=3.7
License-File: LICENSE
Requires-Dist: colored
Provides-Extra: docs
Requires-Dist: sphinx ; extra == 'docs'
Requires-Dist: sphinx-rtd-theme ; extra == 'docs'
Requires-Dist: sphinx-autorun ; extra == 'docs'
Requires-Dist: sphinxcontrib-jsmath ; extra == 'docs'
Requires-Dist: sphinx-markdown-tables ; extra == 'docs'
Requires-Dist: sphinx-autodoc-typehints ; extra == 'docs'
Requires-Dist: sphinx-favicon ; extra == 'docs'
